ambit/__init__.py
ambit/component.py
ambit/configuration.py
ambit/controller.py
ambit/coordinates.py
ambit/fake.py
ambit/flags.py
ambit/image.py
ambit/message.py
ambit/render.py
ambit/resources.py
ambit/simulator.py
ambit/resources/assets/23.png
ambit/resources/assets/23.raw
ambit/resources/assets/24.png
ambit/resources/assets/24.raw
ambit/resources/assets/25.png
ambit/resources/assets/25.raw
ambit/resources/assets/reference/0.raw
ambit/resources/assets/reference/1.raw
ambit/resources/assets/reference/10.raw
ambit/resources/assets/reference/11.raw
ambit/resources/assets/reference/12.raw
ambit/resources/assets/reference/13.raw
ambit/resources/assets/reference/14.raw
ambit/resources/assets/reference/15.raw
ambit/resources/assets/reference/16.raw
ambit/resources/assets/reference/17.raw
ambit/resources/assets/reference/18.raw
ambit/resources/assets/reference/19.raw
ambit/resources/assets/reference/2.raw
ambit/resources/assets/reference/20.raw
ambit/resources/assets/reference/21.raw
ambit/resources/assets/reference/22.raw
ambit/resources/assets/reference/3.raw
ambit/resources/assets/reference/4.raw
ambit/resources/assets/reference/5.raw
ambit/resources/assets/reference/6.raw
ambit/resources/assets/reference/7.raw
ambit/resources/assets/reference/8.raw
ambit/resources/assets/reference/9.raw
ambit/resources/layouts/hidmap.plp
ambit/resources/layouts/multifunction-buttons/00-meta.plp
ambit/resources/layouts/multifunction-buttons/01-hack.plp
ambit/resources/layouts/multifunction-buttons/02-music.plp
ambit/resources/layouts/multifunction-buttons/03-home.plp
ambit/resources/layouts/multifunction-dial/00-meta.plp
ambit/resources/layouts/multifunction-dial/01-hack.plp
ambit/resources/layouts/multifunction-dial/03-home.plp
ambit/resources/layouts/multifunction-slider/00-meta.plp
ambit/resources/layouts/multifunction-slider/01-hack.plp
ambit/resources/layouts/multifunction-slider/03-home.plp
ambit/resources/layouts/showcase/00-meta.plp
ambit/resources/layouts/showcase/01-hack.plp
ambit-0.3.6.dist-info/LICENSE
ambit-0.3.6.dist-info/METADATA
ambit-0.3.6.dist-info/WHEEL
ambit-0.3.6.dist-info/top_level.txt
ambit-0.3.6.dist-info/RECORD
