Metadata-Version: 2.1
Name: ambit
Version: 0.3.6
Summary: Take control of your Palette.
Home-page: https://github.com/khimaros/ambit
Author: khimaros
License: UNKNOWN
Keywords: monogramcc,palettegear,demoscene,pygame,linux,pyusb
Platform: UNKNOWN
Classifier: Development Status :: 3 - Alpha
Classifier: Programming Language :: Python :: 3
Classifier: License :: OSI Approved :: GNU General Public License v3 (GPLv3)
Classifier: Operating System :: POSIX
Classifier: Topic :: System :: Hardware
Requires-Python: >=3.6
License-File: LICENSE
